{
    "locations": [
        {
            "id":0,
            "title": "Near Ras id-Dawwara",
            "description": "Located on the western coast of Malta, <b>Ras id-Dawwara</b> is celebrated for its panoramic views and serene landscapes. This coastal promontory is a prime spot for hiking and photography, offering sweeping vistas of the Mediterranean Sea and dramatic cliff formations. The area is also known for its spectacular sunsets, making it a perfect location for evening walks and nature appreciation.",
            "img": "/assets/images/places/6.png",
            "lon": 14.355620,
            "lat": 35.866722,
            "url": "https://www.instagram.com/reel/C6UC2RUoSjx/embed"
        },
        {
            "id":1,
            "title": "Blue Grotto",
            "description": "The <b>Blue Grotto</b> is renowned for its stunning azure waters and impressive natural arches, located on the southern coast of Malta near the village of Żurrieq. Accessible by boat, this network of sea caverns mirrors the phosphorescent colors of the underwater flora. The grotto and surrounding area are popular for snorkeling, diving, and boat trips, offering visitors a breathtaking view of the clear, blue sea against a backdrop of high cliffs.",
            "img": "/assets/images/places/3.png",
            "lon": 14.4562387,
            "lat": 35.8207177,
            "url": "https://www.instagram.com/reel/CzWSytWM385/embed"
        },
        {
            "id":2,
            "title": "Il-Mara",
            "description": "Il Mara, located between Fort Benghajsa and Ghar Hasan beneath the impressive cliffs, is a beautiful but less-traveled spot ideal for hiking. The area's remote location means fewer visitors and a peaceful hiking experience. The cliffs offer dramatic views of the surrounding landscape, and the terrain provides a moderate challenge suitable for most hikers looking for an adventure off the beaten path.",
            "img": "/assets/images/places/2.png",
            "lon": 14.5305347,
            "lat": 35.8065369,
            "url": "https://www.instagram.com/reel/C2zz_hjMcY-/embed"
        },
        {
            "id":3,
            "title": "Għar ir-Riħ",
            "description": "<b>Għar ir-Riħ</b> is in front of one of the cliff passages whose mouth is hidden behind a large rock. As you enter it you will find various rock formations that have formed over the years. At the end of it comes to another mouth that overlooks the sea with wonderful views.",
            "img": "/assets/images/places/0.png",
            "lon": 14.525437010570169,
            "lat": 35.80702570126614,
            "url": "https://www.instagram.com/reel/C4_IILpoxRx/embed"
        },
        {
            "id":4,
            "title": "Ras Il-Mignuna Window",
            "description": "This is a Natural Arch at <b>Ras Il-Mignuna</b> located on the coast of Qrendi, between Wied iż-Żurrieq and Għar Lapsi",
            "img": "/assets/images/places/1.jpg",
            "lon": 14.438552453233333,
            "lat": 35.822497835426105,
            "url": "https://www.instagram.com/reel/C4vmiFnorW3/embed"
        },
        {
            "id":5,
            "title": "Ras id-Dawwara",
            "description": "Located on the western coast of Malta, <b>Ras id-Dawwara</b> is celebrated for its panoramic views and serene landscapes. This coastal promontory is a prime spot for hiking and photography, offering sweeping vistas of the Mediterranean Sea and dramatic cliff formations. The area is also known for its spectacular sunsets, making it a perfect location for evening walks and nature appreciation.",
            "img": "/assets/images/places/4.jpg",
            "lon": 14.3536699,
            "lat": 35.8681994,
            "url": "https://www.instagram.com/reel/C4GkCUZM1Zp/embed"
        },
        {
            "id":6,
            "title": "Popeye Village",
            "description": "Originally constructed as a film set for the 1980 movie 'Popeye', <b>Popeye Village</b> has since transformed into a colorful and vibrant amusement park. Located at Anchor Bay in the north-west of Malta, this unique attraction offers a glimpse into the quirky world of Popeye the Sailor. Visitors can explore the rustic wooden buildings, take part in various themed activities, and enjoy shows and boat rides. The bay also offers stunning views, making it a fun and picturesque destination for families and tourists alike.",
            "img": "/assets/images/places/5.jpg",
            "lon": 14.341693,
            "lat": 35.960651,
            "url": "https://www.instagram.com/reel/C4OF8cKMavp/embed"
        },
        {
            "id":7,
            "title": "Elephant Rock",
            "description": "Elephant Rock is a stunning natural rock formation that resembles the shape of an elephant. Located along Malta's picturesque coastline, this geological wonder is a favorite spot for photographers and nature lovers. The area around Elephant Rock offers scenic walks and the opportunity to explore secluded coves and crystal-clear waters.",
            "img": "/assets/images/places/7.jpg",
            "lon": 14.346907885575565,
            "lat": 36.01422213881614,
            "url": "https://www.instagram.com/reel/C6BwwfTIXFm/embed"
        },
        {
            "id":8,
            "title": "Munxar Path",
            "description": "Munxar Path is a scenic coastal walk in Marsaskala, offering breathtaking views of the Mediterranean Sea and the rugged Maltese coastline. This trail is perfect for nature enthusiasts and walkers who enjoy peaceful, picturesque landscapes. Along the path, hikers can observe local flora and fauna, explore small, hidden coves, and enjoy tranquil moments by the sea.",
            "img": "/assets/images/places/8.jpg",
            "lon": 14.570848,
            "lat": 35.849367,
            "url": "https://www.instagram.com/reel/C5ftOgOIvYz/embed"
        },
        {
            "id":9,
            "title": "Munxar Window",
            "description": "The Munxar Window is a striking natural arch located along the rugged coastline of Malta, near Marsaskala. This impressive geological formation offers a unique sight, especially popular among photographers and nature enthusiasts. The area around the Munxar Window is ideal for scenic hikes and provides panoramic views of the surrounding sea and landscape, making it a must-visit for those seeking the beauty of Malta's natural wonders.",
            "img": "/assets/images/places/9.JPG",
            "lon": 14.5698237,
            "lat": 35.8499062,
            "url": "https://www.instagram.com/reel/C38LNq3McjE/embed"
        },
        {
            "id":10,
            "title": "Hofriet Window",
            "description": "Hofriet Window, also known as the 'Blue Cave', is one of Malta's lesser-known yet captivating natural arches, located near the southern coast. This secluded spot is accessible primarily by boat and offers a unique blend of azure waters and dramatic rock formations. The tranquility and natural beauty of the area make it an ideal destination for those looking to escape the more crowded tourist spots and enjoy some of Malta's pristine marine environment.",
            "img": "/assets/images/places/10.jpg",
            "lon": 14.563689974293295,
            "lat": 35.83819204033,
            "url": "https://www.instagram.com/reel/C3nYoDeMwf_/embed"
        },
        {
            "id":11,
            "title": "Bighi Cot-Lift",
            "description": "The Bighi Cot-Lift, part of the historical Bighi Royal Naval Hospital in Kalkara, is a remarkable example of early 20th-century engineering. Initially used to transport patients and goods between the hospital and the waterfront, the cot-lift is now a unique cultural heritage site that attracts visitors interested in the technological innovations of the past. The surrounding area offers stunning views of the Grand Harbour, making it a worthwhile visit for history buffs and those enjoying scenic landscapes.",
            "img": "/assets/images/places/11.jpg",
            "lon": 14.5244437,
            "lat": 35.8919094,
            "url": "https://www.instagram.com/reel/C7XgkJsMjFp/embed"
        },
        {
            "id":12,
            "title": "Wied il-Għasel",
            "description": "Wied il-Għasel, which translates to 'Valley of Honey' in Maltese, is one of the longest valleys located in the northern region of Malta, near Mosta. This picturesque valley is renowned for its lush vegetation, seasonal streams, and historical significance, including several ancient cart ruts and a mysterious network of tunnels. It is a favorite among hikers and nature lovers for its serene environment and the diverse flora and fauna that can be explored throughout the year.",
            "img": "/assets/images/places/12.jpg",
            "lon": 14.4250258,
            "lat": 35.9155058,
            "url": "https://www.instagram.com/reel/C30t3rOMBVB/embed"
        },
        {
            "id":13,
            "title": "Coral Lagoon",
            "description": "Coral Lagoon, located near Mellieħa on the northern coast of Malta, is a stunning natural wonder renowned for its crystal-clear waters and unique circular shape. This secluded lagoon is accessible via a hole in its rocky roof or by sea kayak, making it an adventurous spot for explorers and water sports enthusiasts. The Coral Lagoon is a perfect location for snorkeling, where one can observe a variety of marine life in a tranquil, almost untouched environment.",
            "img": "/assets/images/places/13.jpg",
            "lon": 14.367659,
            "lat": 35.997909,
            "url": "https://www.instagram.com/reel/C7M0_gtOLJN/embed"
        },
        {
            "id":14,
            "title": "Il-Ġebla l-Imtaqqba",
            "description": "Il-Ġebla l-Imtaqqba, also known as the 'Punctured Rock', is a striking natural landmark located along the picturesque coast of Malta. This unique rock formation is noted for its distinctive hole that goes right through it, creating a natural window to the sea beyond. The site is a popular spot for photographers and nature enthusiasts, offering breathtaking views especially at sunset. The area around Il-Ġebla l-Imtaqqba also provides excellent opportunities for hiking and enjoying the tranquil Mediterranean landscape.",
            "img": "/assets/images/places/16.jpg",
            "lon": 14.325799,
            "lat": 36.010848,
            "url": "https://www.instagram.com/reel/C5yJsAaIdk4/embed"
        },
        {
            "id":15,
            "title": "Paradise Bay",
            "description": "Paradise Bay, located at the northern tip of Malta near Ċirkewwa, is one of the island's most picturesque beaches. Known for its crystal-clear waters and fine sandy beach, this secluded cove is surrounded by rugged cliffs that provide shelter and create a tranquil, almost private beach atmosphere. Paradise Bay is ideal for swimming, sunbathing, and snorkeling, making it a favorite among both locals and tourists seeking a serene getaway. The bay also features amenities such as a restaurant and beach equipment rentals, enhancing the comfort and convenience of your visit.",
            "img": "/assets/images/places/17.png",
            "lon": 14.332826579817256,
            "lat": 35.98227580320132,
            "url": "https://www.instagram.com/reel/CxBX5csMihe/embed"
        },
        {
            "id":16,
            "title": "L-Għar ta’ Bla Saqaf",
            "description": "L-Għar ta’ Bla Saqaf, translating to 'The Cave Without a Ceiling' in English, is a remarkable open-air cave located in the limits of Mellieħa. This unique geological formation is known for its impressive natural arch and panoramic views of the surrounding countryside and coastline. The cave is a popular destination for hikers and nature lovers who come to explore its rugged beauty and enjoy the serene atmosphere that the area offers.",
            "img": "/assets/images/places/15.jpg",
            "lon": 14.329411,
            "lat": 36.009697,
            "url": "https://www.instagram.com/reel/C6eVS0GoPf9/embed"
        },
        {
            "id":17,
            "title": "Natural Window",
            "description": "This natural window is located in Comino near a historic coastal fortification on the northern coast of Malta, called 'Il-Batterija ta' Santa Marija'",
            "img": "/assets/images/places/18.jpg",
            "lon": 14.347281410906533,
            "lat": 36.00631138767528,
            "url": "https://www.instagram.com/reel/C6_Sb24oiEs/embed"
        },
        {
            "id":18,
            "title": "Mistra Bay",
            "description": "Mistra Bay, located in the northern part of Malta, is a tranquil and picturesque bay known for its clear, shallow waters and pebble beach. This serene spot is ideal for swimming, snorkeling, and relaxing by the sea. Surrounded by natural beauty and historical sites, such as the Mistra Battery, the bay offers a perfect blend of leisure and exploration. The calm waters and peaceful atmosphere make Mistra Bay a hidden gem, providing a great escape from the more crowded tourist spots.",
            "img": "/assets/images/places/22.JPG",
            "lon": 14.391039725356249,
            "lat": 35.957417736969006,
            "url": "https://www.instagram.com/reel/CuxB6E-N3nR/embed"
        },              
        {
            "id":19,
            "title": "Dingli Cliffs",
            "description": "Dingli Cliffs, located on the western coast of Malta, are one of the island's most breathtaking natural landmarks. Rising over 250 meters above sea level, these dramatic cliffs offer stunning panoramic views of the Mediterranean Sea and the surrounding countryside. The area is perfect for hiking and enjoying spectacular sunsets. Visitors can also explore nearby attractions, such as the small chapel of St. Mary Magdalene, perched right on the edge of the cliffs. Dingli Cliffs provide a serene and awe-inspiring experience for nature lovers and photographers alike.",
            "img": "/assets/images/places/21.JPG",
            "lon": 14.39847475818653,
            "lat": 35.84141667763579,
            "url": "https://www.instagram.com/reel/Cty1LJ5MPQj/embed"
        },
        {
            "id":20,
            "title": "White Rocks",
            "description": "White Rocks is a stunning coastal area located on the northeastern coast of Malta. Known for its striking white limestone formations, this area offers breathtaking views of the Mediterranean Sea and a unique landscape perfect for photography and exploration. The White Rocks area is a popular spot for hikers and nature enthusiasts who come to enjoy the scenic beauty and the serene atmosphere. Whether you're looking to take a leisurely walk along the coast or explore the rocky terrain, White Rocks provides a memorable outdoor experience.",
            "img": "/assets/images/places/20.png",
            "lon": 14.469458617253675,
            "lat": 35.93356783527314,
            "url": "https://www.instagram.com/reel/C9fGqT3MlKT/embed"
        },
        {
            "id":21,
            "title": "St. Mark's Tower",
            "description": "St. Mark's Tower, also known as Qalet Marku Tower, is a historic watchtower located on the northeastern coast of Malta. Built in the 17th century by the Order of Saint John, this coastal fortification was part of a network of towers used to defend the island against invaders. Today, St. Mark's Tower stands as a testament to Malta's rich history, offering visitors a glimpse into the past. The tower is situated in a scenic area with beautiful views of the Mediterranean Sea, making it a popular spot for history enthusiasts and photographers.",
            "img": "/assets/images/places/23.jpg",
            "lon": 14.453294928876327,
            "lat": 35.94647468280512,
            "url": "https://www.instagram.com/reel/CpGJ1gggRbR/embed"
        },  
        {
            "id":22,
            "title": "Għar iċ-Ċomb",
            "description": "Għar iċ-Ċomb, also known as the 'Lead Cave', is a fascinating natural cave located in the scenic countryside of Malta. This cave is renowned for its intriguing rock formations and historical significance, having been used in ancient times for various purposes. Visitors to Għar iċ-Ċomb can explore its depths and admire the natural beauty and geological features that make it a unique spot. The surrounding area also offers picturesque views and opportunities for hiking and nature walks.",
            "img": "/assets/images/places/19.JPG",
            "lon": 14.372112708186386,
            "lat": 35.99309133941263,
            "url": "https://www.instagram.com/johnfabiomb/embed"
        }        
    ]
}